{
	"configurations" : 
	[
		{
			"directories" : 
			[
				{
					"build" : ".",
					"jsonFile" : "directory-.-Debug-d0094a50bb2071803777.json",
					"minimumCMakeVersion" : 
					{
						"string" : "3.28"
					},
					"projectIndex" : 0,
					"source" : ".",
					"targetIndexes" : 
					[
						0
					]
				}
			],
			"name" : "Debug",
			"projects" : 
			[
				{
					"directoryIndexes" : 
					[
						0
					],
					"name" : "university_intro_to_programming_pp",
					"targetIndexes" : 
					[
						0
					]
				}
			],
			"targets" : 
			[
				{
					"directoryIndex" : 0,
					"id" : "university_intro_to_programming_pp::@6890427a1f51a3e7e1df",
					"jsonFile" : "target-university_intro_to_programming_pp-Debug-e1632fd601180085d7e6.json",
					"name" : "university_intro_to_programming_pp",
					"projectIndex" : 0
				}
			]
		}
	],
	"kind" : "codemodel",
	"paths" : 
	{
		"build" : "C:/Users/jabaclaw4/CLionProjects/university-intro-to-programming-\u0421pp/cmake-build-debug",
		"source" : "C:/Users/jabaclaw4/CLionProjects/university-intro-to-programming-\u0421pp"
	},
	"version" : 
	{
		"major" : 2,
		"minor" : 6
	}
}
